[
    {
        "name": "OscarCito",
        "surname": "Monomulo",
        "email": "oscarmonumolo@gmail.com",
        "password": "$2a$10$xXLMQX58hDIoHRDpj2bOVub5A0EPuFY6YLmT99GRiIZgkPPOFnEGy",
        "confirmpassword": "$2a$10$BOsushqU0AEuHGtTj9Jy4uLE/sEidV9RHz25cIv2YFMPwVi7HdSjy",
        "birthdate": "",
        "phonenumber": "",
        "country": "",
        "state": "",
        "address": "",
        "creditcard": "",
        "creditcardowner": "",
        "expirancy": "",
        "bancacount": "",
        "bancacountowner": "",
        "bancexpirancy": "",
        "id": "6c34af12-5acf-49ea-bfe4-a0121187b186"
    },
    {
        "name": "Pedrooooo",
        "surname": "Gomez",
        "email": "pedrogomez@hotmail.com",
        "password": "$2a$10$kfO4lsHqv0Ynnq3zKvdcx.JjZVvVjBwLPJhRn9ymTb6GHLZOBZNUa",
        "confirmpassword": "$2a$10$Lv4ZVDgpDdNpskFQWTI3Ve8pCMgKI7ZbadM1lqKDAZxSb.1pvGxem",
        "birthdate": "",
        "phonenumber": "1555555555",
        "country": "",
        "state": "",
        "address": "",
        "creditcard": "",
        "creditcardowner": "",
        "expirancy": "",
        "bancacount": "",
        "bancacountowner": "",
        "bancexpirancy": "",
        "id": "1e98a6c6-8c25-473b-8679-cd6bd5be5099"
    },
    {
        "name": "Agus",
        "surname": "Ramirez",
        "email": "agusramirez@hotmail.com",
        "password": "$2a$10$i8gd9DE9HtHvUfWQcjaWyuoOlN9fzvNLCs6/BsCke1VM9te/Q0/l.",
        "confirmpassword": "$2a$10$kQW3CxA1NcIkUrLz1ZzDOuH.bM7k/vSgI/DXFp4kZq6yVWWgA8aJ6",
        "birthdate": "",
        "phonenumber": "",
        "country": "",
        "state": "",
        "address": "",
        "creditcard": "",
        "creditcardowner": "",
        "expirancy": "",
        "bancacount": "",
        "bancacountowner": "",
        "bancexpirancy": "",
        "id": "18fe1d6c-09f5-4296-9b98-0c7747a39e13"
    }
]